bitgeist/__init__.py
bitgeist/layers.py
bitgeist/pytorch_transform.py
bitgeist/resources/ctemplate.tpl.c
bitgeist/transform.py
bitgeist-0.1.3.dist-info/WHEEL
bitgeist-0.1.3.dist-info/METADATA
bitgeist-0.1.3.dist-info/RECORD
