Metadata-Version: 2.1
Name: bitgeist
Version: 0.1.3
Summary: bitgeist is a Python library to convert deep neural network models into c source code.
Author: germar
Author-email: g.schlegel@geisten.com
Requires-Python: >=3.7.12,<4.0.0
Classifier: Programming Language :: Python :: 3
Classifier: Programming Language :: Python :: 3.8
Classifier: Programming Language :: Python :: 3.9
Classifier: Programming Language :: Python :: 3.10
Requires-Dist: torch (>=1.10.0,<2.0.0)
